textimp2-0.1.0.dist-info/METADATA
textimp2-0.1.0.dist-info/WHEEL
textimp2-0.1.0.dist-info/entry_points.txt
textimp2/contacts.py
textimp2/_core.pyi
textimp2/__init__.py
textimp2/_core.cpython-312-darwin.so
textimp2-0.1.0.dist-info/RECORD
