Metadata-Version: 2.4
Name: textimp2
Version: 0.1.0
Requires-Dist: pandas>=2.3.3
Requires-Dist: polars>=1.37.1
Requires-Dist: pyarrow>=23.0.0
Summary: A Python library for interacting with iMessage data, built using Rust and Apache Arrow.
Author-email: Adam Gluck <adam.gluck10@gmail.com>
Requires-Python: >=3.12
